verbomate/__init__.py
verbomate/main.py
verbomate-0.1.7.dist-info/LICENSE.md
verbomate-0.1.7.dist-info/METADATA
verbomate-0.1.7.dist-info/WHEEL
verbomate-0.1.7.dist-info/entry_points.txt
verbomate-0.1.7.dist-info/top_level.txt
verbomate-0.1.7.dist-info/RECORD
