Metadata-Version: 2.1
Name: verbomate
Version: 0.1.7
Summary: Generate and run python scripts from your command line
Home-page: https://github.com/gordbegli/verbomate
Author: Gabriel Gordbegli
Author-email: gabe@gordbegli.com
License: MIT
License-File: LICENSE.md
Requires-Dist: requests
Requires-Dist: openai
Requires-Dist: argparse
